README.rst
setup.py
draft/__init__.py
draft/cli.py
draft/formatter.py
draft/generator.py
draft/helpers.py
draft/outliner.py
draft_cli.egg-info/PKG-INFO
draft_cli.egg-info/SOURCES.txt
draft_cli.egg-info/dependency_links.txt
draft_cli.egg-info/entry_points.txt
draft_cli.egg-info/requires.txt
draft_cli.egg-info/top_level.txt
tests/__init__.py
tests/test_cli.py
tests/test_formatter.py
tests/test_generator.py
tests/test_helpers.py
tests/test_outliner.py