Metadata-Version: 1.1
Name: draft-cli
Version: 0.1
Summary: CLI-enabled writing system to keep your work modular and optimize your files for git for version control.
Home-page: https://github.com/edelgm6/draft
Author: Garrett Edel
Author-email: edelgm6@gmail.com
License: UNKNOWN
Platform: UNKNOWN
Classifier: Programming Language :: Python :: 3
Classifier: License :: OSI Approved :: GNU General Public License v3 (GPLv3)
Classifier: Operating System :: OS Independent
